amulet/utils/__init__.py
amulet/utils/_utils.cpython-311-darwin.so
amulet/utils/_utils.pyi
amulet/utils/_version.py
amulet/utils/amulet_utilsConfig.cmake
amulet/utils/dll.hpp
amulet/utils/libamulet_utils.dylib
amulet/utils/lock.pyi
amulet/utils/lock_file.hpp
amulet/utils/memory.hpp
amulet/utils/mutex.hpp
amulet/utils/numpy.hpp
amulet/utils/numpy.pyi
amulet/utils/python.hpp
amulet/utils/temp.hpp
amulet/utils/weak.hpp
amulet/utils/logging/__init__.pyi
amulet/utils/logging/_logging.py
amulet/utils/logging/logging.hpp
amulet/utils/signal/__init__.py
amulet/utils/signal/_connection_mode.pyi
amulet/utils/signal/signal.hpp
amulet/utils/signal/signal.py.hpp
amulet/utils/task_manager/__init__.pyi
amulet/utils/task_manager/cancel_manager.hpp
amulet/utils/task_manager/cancel_manager.pyi
amulet/utils/task_manager/progress_manager.hpp
amulet/utils/task_manager/progress_manager.pyi
amulet_utils-1.0.0.dist-info/licenses/LICENSE
amulet_utils-1.0.0.dist-info/METADATA
amulet_utils-1.0.0.dist-info/WHEEL
amulet_utils-1.0.0.dist-info/top_level.txt
amulet_utils-1.0.0.dist-info/RECORD
