Metadata-Version: 2.4
Name: amulet-utils
Version: 1.0.0
Summary: A C++ utility library with a python wrapper.
Author: James Clare
Project-URL: Homepage, https://www.amuletmc.com
Project-URL: Repository, https://github.com/Amulet-Team/Amulet-Utils
Project-URL: Issues, https://github.com/Amulet-Team/Amulet-Utils/issues
Classifier: Programming Language :: Python :: 3
Classifier: Operating System :: OS Independent
Requires-Python: >=3.11
License-File: LICENSE
Requires-Dist: amulet-compiler-target==1.0
Requires-Dist: platformdirs~=3.1
Requires-Dist: amulet-compiler-version==1.3.0.1297307203.19.43.34808.0
Requires-Dist: amulet_pybind11_extensions~=1.0.0.0
Provides-Extra: dev
Requires-Dist: setuptools>=42; extra == "dev"
Requires-Dist: versioneer; extra == "dev"
Requires-Dist: wheel; extra == "dev"
Requires-Dist: numpy~=2.0; extra == "dev"
Requires-Dist: pybind11==2.13.6; extra == "dev"
Requires-Dist: amulet-test-utils~=1.0; extra == "dev"
Requires-Dist: pybind11_stubgen; extra == "dev"
Requires-Dist: black>=22.3; extra == "dev"
Requires-Dist: isort; extra == "dev"
Requires-Dist: autoflake; extra == "dev"
Requires-Dist: mypy; extra == "dev"
Requires-Dist: types-pyinstaller; extra == "dev"
Dynamic: license-file
Dynamic: requires-dist
